{
  "logger": {
    "currentLogLevel": 20,
    "name": "root.bean.benchmarks.Defects4JBug"
  },
  "d4jCmd": "/path/to/defects4j/framework/bin/defects4j",
  "dataDir": "data/changesInfo/",
  "properties": {
    "trigger.tests": "org.jfree.chart.plot.junit.ValueMarkerTests::test1808376",
    "test.dir": "tests",
    "clz.modified": "org.jfree.chart.plot.ValueMarker",
    "src.dir": "source"
  },
  "timeoutSecond": 100,
  "proj": "Chart",
  "id": "20",
  "workingDir": "../bugs/Chart_20_tmp",
  "bug_name": "Chart_20",
  "derive": "defects4j",
  "trigger_tests": [
    {
      "test_class": "org.jfree.chart.plot.junit.ValueMarkerTests",
      "test_function": "test1808376",
      "assertion_line": "297",
      "exception": "junit.framework.AssertionFailedError",
      "message": "expected:\u003cjava.awt.Color[r\u003d0,g\u003d0,b\u003d255]\u003e but was:\u003cjava.awt.Color[r\u003d255,g\u003d0,b\u003d0]\u003e"
    }
  ],
  "fixing_changes": [
    {
      "changed_type": "UPDATE",
      "changed_class": [
        "source/org/jfree/chart/plot/ValueMarker.java",
        "source/org/jfree/chart/plot/ValueMarker.java"
      ],
      "changed_functions": [
        {
          "qualified_names": [
            "org.jfree.chart.plot.ValueMarker:ValueMarker:[double value, Paint paint, Stroke stroke, Paint outlinePaint, Stroke outlineStroke, float alpha]:null"
          ],
          "num": 1
        },
        {
          "qualified_names": [
            "org.jfree.chart.plot.ValueMarker:ValueMarker:[double value, Paint paint, Stroke stroke, Paint outlinePaint, Stroke outlineStroke, float alpha]:null"
          ],
          "num": 1
        }
      ],
      "changed_lines": [
        {
          "qualified_names": [
            "95"
          ],
          "num": 1
        },
        {
          "qualified_names": [
            "95"
          ],
          "num": 1
        }
      ],
      "diff": "diff --git a/source/org/jfree/chart/plot/ValueMarker.java b/source/org/jfree/chart/plot/ValueMarker.java\nindex 58d5289..075683d 100644\n--- a/source/org/jfree/chart/plot/ValueMarker.java\n+++ b/source/org/jfree/chart/plot/ValueMarker.java\n@@ -92,7 +92,7 @@\n      */\r\n     public ValueMarker(double value, Paint paint, Stroke stroke, \r\n                        Paint outlinePaint, Stroke outlineStroke, float alpha) {\r\n-        super(paint, stroke, outlinePaint, outlineStroke, alpha);\r\n+        super(paint, stroke, paint, stroke, alpha);\r\n         this.value \u003d value;\r\n     }\r\n     \r\n",
      "operations": [
        {
          "type": "update-node",
          "from": "",
          "to": ""
        },
        {
          "type": "update-node",
          "from": "",
          "to": ""
        }
      ]
    }
  ],
  "fixing_type": {
    "add_classes": {
      "qualified_names": [],
      "num": 0
    },
    "delete_classes": {
      "qualified_names": [],
      "num": 0
    },
    "add_functions": {
      "qualified_names": [],
      "num": 0
    },
    "delete_functions": {
      "qualified_names": [],
      "num": 0
    }
  }
}