{
  "logger": {
    "currentLogLevel": 20,
    "name": "root.bean.benchmarks.Defects4JBug"
  },
  "d4jCmd": "/path/to/defects4j/framework/bin/defects4j",
  "dataDir": "data/changesInfo/",
  "properties": {
    "trigger.tests": "com.google.javascript.jscomp.CheckGlobalNamesTest::testGlobalCatch",
    "test.dir": "test",
    "clz.modified": "com.google.javascript.jscomp.GlobalNamespace",
    "src.dir": "src"
  },
  "timeoutSecond": 100,
  "proj": "Closure",
  "id": "119",
  "workingDir": "../bugs/Closure_119_tmp",
  "bug_name": "Closure_119",
  "derive": "defects4j",
  "trigger_tests": [
    {
      "test_class": "com.google.javascript.jscomp.CheckGlobalNamesTest",
      "test_function": "testGlobalCatch",
      "assertion_line": "341",
      "exception": "junit.framework.AssertionFailedError",
      "message": "Unexpected warning(s): JSC_UNDEFINED_NAME. e is never defined at testcode line 1 : 48"
    }
  ],
  "fixing_changes": [
    {
      "changed_type": "UPDATE",
      "changed_class": [
        "src/com/google/javascript/jscomp/GlobalNamespace.java",
        "src/com/google/javascript/jscomp/GlobalNamespace.java"
      ],
      "changed_functions": [
        {
          "qualified_names": [
            "com.google.javascript.jscomp.GlobalNamespace\\$BuildGlobalNamespace:collect:[JSModule module, Scope scope, Node n]:void"
          ],
          "num": 1
        },
        {
          "qualified_names": [
            "com.google.javascript.jscomp.GlobalNamespace\\$BuildGlobalNamespace:collect:[JSModule module, Scope scope, Node n]:void"
          ],
          "num": 1
        }
      ],
      "changed_lines": [
        {
          "qualified_names": [
            "366"
          ],
          "num": 1
        },
        {
          "qualified_names": [
            "365"
          ],
          "num": 1
        }
      ],
      "diff": "diff --git a/src/com/google/javascript/jscomp/GlobalNamespace.java b/src/com/google/javascript/jscomp/GlobalNamespace.java\nindex 0e9c4d3..639318d 100644\n--- a/src/com/google/javascript/jscomp/GlobalNamespace.java\n+++ b/src/com/google/javascript/jscomp/GlobalNamespace.java\n@@ -363,7 +363,6 @@\n                 isSet \u003d true;\n                 type \u003d Name.Type.FUNCTION;\n                 break;\n-              case Token.CATCH:\n               case Token.INC:\n               case Token.DEC:\n                 isSet \u003d true;\n",
      "operations": [
        {
          "type": "delete-tree",
          "from": "SwitchCase [11141,11158]",
          "to": ""
        }
      ]
    }
  ],
  "fixing_type": {
    "add_classes": {
      "qualified_names": [],
      "num": 0
    },
    "delete_classes": {
      "qualified_names": [],
      "num": 0
    },
    "add_functions": {
      "qualified_names": [],
      "num": 0
    },
    "delete_functions": {
      "qualified_names": [],
      "num": 0
    }
  }
}