{
  "logger": {
    "currentLogLevel": 20,
    "name": "root.bean.benchmarks.Defects4JBug"
  },
  "d4jCmd": "/path/to/defects4j/framework/bin/defects4j",
  "dataDir": "data/changesInfo/",
  "properties": {
    "trigger.tests": "org.apache.commons.math3.optimization.univariate.BrentOptimizerTest::testMath855",
    "test.dir": "src/test/java",
    "clz.modified": "org.apache.commons.math3.optimization.univariate.BrentOptimizer",
    "src.dir": "src/main/java"
  },
  "timeoutSecond": 100,
  "proj": "Math",
  "id": "24",
  "workingDir": "../bugs/Math_24_tmp",
  "bug_name": "Math_24",
  "derive": "defects4j",
  "trigger_tests": [
    {
      "test_class": "org.apache.commons.math3.optimization.univariate.BrentOptimizerTest",
      "test_function": "testMath855",
      "assertion_line": "213",
      "exception": "junit.framework.AssertionFailedError",
      "message": "Best point not reported"
    }
  ],
  "fixing_changes": [
    {
      "changed_type": "UPDATE",
      "changed_class": [
        "src/main/java/org/apache/commons/math3/optimization/univariate/BrentOptimizer.java",
        "src/main/java/org/apache/commons/math3/optimization/univariate/BrentOptimizer.java"
      ],
      "changed_functions": [
        {
          "qualified_names": [
            "org.apache.commons.math3.optimization.univariate.BrentOptimizer:doOptimize:[]:UnivariatePointValuePair"
          ],
          "num": 1
        },
        {
          "qualified_names": [
            "org.apache.commons.math3.optimization.univariate.BrentOptimizer:doOptimize:[]:UnivariatePointValuePair"
          ],
          "num": 1
        }
      ],
      "changed_lines": [
        {
          "qualified_names": [
            "230",
            "267"
          ],
          "num": 2
        },
        {
          "qualified_names": [
            "230",
            "267"
          ],
          "num": 2
        }
      ],
      "diff": "diff --git a/src/main/java/org/apache/commons/math3/optimization/univariate/BrentOptimizer.java b/src/main/java/org/apache/commons/math3/optimization/univariate/BrentOptimizer.java\nindex cff5bfd..b6ce68e 100644\n--- a/src/main/java/org/apache/commons/math3/optimization/univariate/BrentOptimizer.java\n+++ b/src/main/java/org/apache/commons/math3/optimization/univariate/BrentOptimizer.java\n@@ -227,7 +227,7 @@\n \n                 if (checker !\u003d null) {\n                     if (checker.converged(iter, previous, current)) {\n-                        return best(current, previous, isMinim);\n+                        return current;\n                     }\n                 }\n \n@@ -264,7 +264,7 @@\n                     }\n                 }\n             } else { // Default termination (Brent\u0027s criterion).\n-                return best(current, previous, isMinim);\n+                return current;\n             }\n             ++iter;\n         }\n",
      "operations": [
        {
          "type": "insert-tree",
          "from": "",
          "to": "ReturnStatement [9360,9375]"
        },
        {
          "type": "insert-tree",
          "from": "",
          "to": "ReturnStatement [8186,8201]"
        },
        {
          "type": "delete-tree",
          "from": "ReturnStatement [8186,8226]",
          "to": ""
        },
        {
          "type": "delete-tree",
          "from": "ReturnStatement [9385,9425]",
          "to": ""
        }
      ]
    }
  ],
  "fixing_type": {
    "add_classes": {
      "qualified_names": [],
      "num": 0
    },
    "delete_classes": {
      "qualified_names": [],
      "num": 0
    },
    "add_functions": {
      "qualified_names": [],
      "num": 0
    },
    "delete_functions": {
      "qualified_names": [],
      "num": 0
    }
  }
}